{"kind":"identitytoolkit#DownloadAccountResponse","users":[{"localId":"MM14Zc7I1blb6412WNY08GUYRmst","createdAt":"1680967048654","lastLoginAt":"1680967048654","passwordHash":"fakeHash:salt=fakeSaltkEsBL3drIbnfvXlm1H7p:password=PASSWORD","salt":"fakeSaltkEsBL3drIbnfvXlm1H7p","passwordUpdatedAt":1681140847279,"providerUserInfo":[{"providerId":"password","email":"friend3@test.com","federatedId":"friend3@test.com","rawId":"friend3@test.com"}],"validSince":"1681140847","email":"friend3@test.com","emailVerified":false,"disabled":false},{"localId":"h7tEDG4d1y1H7usGRSQo7P3X9KWw","createdAt":"1680967054238","lastLoginAt":"1680967054238","passwordHash":"fakeHash:salt=fakeSaltSv14ddFKbwRkgm94Ydqo:password=PASSWORD","salt":"fakeSaltSv14ddFKbwRkgm94Ydqo","passwordUpdatedAt":1681140847279,"providerUserInfo":[{"providerId":"password","email":"friend4@test.com","federatedId":"friend4@test.com","rawId":"friend4@test.com"}],"validSince":"1681140847","email":"friend4@test.com","emailVerified":false,"disabled":false},{"localId":"h8fc8iF6TJ77xa7Z51AGw2nhPyJi","createdAt":"1680967038673","lastLoginAt":"1680967038673","passwordHash":"fakeHash:salt=fakeSaltfI4ozC8vvtBBczvhVkFr:password=PASSWORD","salt":"fakeSaltfI4ozC8vvtBBczvhVkFr","passwordUpdatedAt":1681140847279,"providerUserInfo":[{"providerId":"password","email":"friend1@test.com","federatedId":"friend1@test.com","rawId":"friend1@test.com"}],"validSince":"1681140847","email":"friend1@test.com","emailVerified":false,"disabled":false},{"localId":"lKa92kcxxJCxVg3LMr0Bhav6Zvxv","createdAt":"1680966939358","lastLoginAt":"1681144097900","passwordHash":"fakeHash:salt=fakeSaltEjX3oXbuSP7L0avDtIQ6:password=password","salt":"fakeSaltEjX3oXbuSP7L0avDtIQ6","passwordUpdatedAt":1681140847279,"providerUserInfo":[{"providerId":"password","email":"ownageunit@gmail.com","federatedId":"ownageunit@gmail.com","rawId":"ownageunit@gmail.com"}],"validSince":"1681140847","email":"ownageunit@gmail.com","emailVerified":false,"disabled":false,"lastRefreshAt":"2023-04-10T16:28:17.900Z"},{"localId":"tS6itkM1mBFcEyWjLFVXYaHba3eC","createdAt":"1680967043100","lastLoginAt":"1680967043100","passwordHash":"fakeHash:salt=fakeSalt9SybY6EgYVcBdt26ca2B:password=PASSWORD","salt":"fakeSalt9SybY6EgYVcBdt26ca2B","passwordUpdatedAt":1681140847279,"providerUserInfo":[{"providerId":"password","email":"friend2@test.com","federatedId":"friend2@test.com","rawId":"friend2@test.com"}],"validSince":"1681140847","email":"friend2@test.com","emailVerified":false,"disabled":false}]}